skyllh/__init__.py
skyllh/_version.py
skyllh/analyses/__init__.py
skyllh/analyses/i3/__init__.py
skyllh/analyses/i3/publicdata_ps/__init__.py
skyllh/analyses/i3/publicdata_ps/aeff.py
skyllh/analyses/i3/publicdata_ps/backgroundpdf.py
skyllh/analyses/i3/publicdata_ps/bkg_flux.py
skyllh/analyses/i3/publicdata_ps/detsigyield.py
skyllh/analyses/i3/publicdata_ps/mcbkg_ps.py
skyllh/analyses/i3/publicdata_ps/pdfratio.py
skyllh/analyses/i3/publicdata_ps/signal_generator.py
skyllh/analyses/i3/publicdata_ps/signalpdf.py
skyllh/analyses/i3/publicdata_ps/smearing_matrix.py
skyllh/analyses/i3/publicdata_ps/time_dependent_ps.py
skyllh/analyses/i3/publicdata_ps/time_integrated_ps.py
skyllh/analyses/i3/publicdata_ps/utils.py
skyllh/cluster/__init__.py
skyllh/cluster/commands.py
skyllh/cluster/compute_node.py
skyllh/cluster/master_node.py
skyllh/cluster/srvclt.py
skyllh/core/__init__.py
skyllh/core/analysis.py
skyllh/core/background_generation.py
skyllh/core/background_generator.py
skyllh/core/backgroundpdf.py
skyllh/core/binning.py
skyllh/core/catalog.py
skyllh/core/config.py
skyllh/core/datafields.py
skyllh/core/dataset.py
skyllh/core/debugging.py
skyllh/core/detsigyield.py
skyllh/core/display.py
skyllh/core/event_selection.py
skyllh/core/expectation_maximization.py
skyllh/core/flux_model.py
skyllh/core/interpolate.py
skyllh/core/livetime.py
skyllh/core/llhratio.py
skyllh/core/math.py
skyllh/core/minimizer.py
skyllh/core/model.py
skyllh/core/multiproc.py
skyllh/core/parameters.py
skyllh/core/pdf.py
skyllh/core/pdfratio.py
skyllh/core/pdfratio_fill.py
skyllh/core/progressbar.py
skyllh/core/py.py
skyllh/core/random.py
skyllh/core/scrambling.py
skyllh/core/services.py
skyllh/core/session.py
skyllh/core/signal_generation.py
skyllh/core/signal_generator.py
skyllh/core/signalpdf.py
skyllh/core/smoothing.py
skyllh/core/source_hypo_grouping.py
skyllh/core/source_model.py
skyllh/core/storage.py
skyllh/core/test_statistic.py
skyllh/core/times.py
skyllh/core/timing.py
skyllh/core/tool.py
skyllh-24.1.0.dist-info/LICENSE.txt
skyllh-24.1.0.dist-info/METADATA
skyllh-24.1.0.dist-info/WHEEL
skyllh-24.1.0.dist-info/top_level.txt
skyllh-24.1.0.dist-info/RECORD
