Metadata-Version: 2.1
Name: skyllh
Version: 24.1.0
Summary: The SkyLLH framework is an open-source Python3-based package licensed under the GPLv3 license. It provides a modular framework for implementing custom likelihood functions and executing log-likelihood ratio hypothesis tests. The idea is to provide a class structure tied to the mathematical objects of the likelihood functions.
Home-page: https://github.com/icecube/skyllh
Author: Martin Wolf
Author-email: martin.wolf@icecube.wisc.edu
License: GPL-3+
Project-URL: Bug Tracker, https://github.com/icecube/skyllh/issues
Project-URL: Documentation, https://icecube.github.io/skyllh
Project-URL: Source Code, https://github.com/icecube/skyllh
Classifier: Development Status :: 5 - Production/Stable
Classifier: Environment :: Console
Classifier: Intended Audience :: Science/Research
Classifier: License :: OSI Approved :: GNU General Public License v3 or later (GPLv3+)
Classifier: Operating System :: POSIX
Classifier: Programming Language :: Python :: 3.8
Classifier: Topic :: Scientific/Engineering :: Physics
License-File: LICENSE.txt
Requires-Dist: astropy
Requires-Dist: numpy
Requires-Dist: scipy
Requires-Dist: tqdm
